flask_live/__init__.py
flask_live-0.0.1.dist-info/LICENSE
flask_live-0.0.1.dist-info/METADATA
flask_live-0.0.1.dist-info/WHEEL
flask_live-0.0.1.dist-info/top_level.txt
flask_live-0.0.1.dist-info/RECORD
