Metadata-Version: 2.1
Name: flask-live
Version: 0.0.1
Summary: Flask Live
Home-page: https://github.com/cn86/flask-live
Author: Conrad Nguyen
Author-email: conradn86@gmail.com
License: GPLv3
Platform: UNKNOWN
